tbot_api/__init__.py
tbot_api/exceptions.py
tbot_api/logger.py
tbot_api/telegram.py
tbot_api/bot/__init__.py
tbot_api/bot/bot.py
tbot_api/bot/methods.py
tbot_api/bot/session.py
tbot_api/enums/__init__.py
tbot_api/enums/bot_command_scope_type.py
tbot_api/enums/chat_action.py
tbot_api/enums/chat_member_status.py
tbot_api/enums/chat_type.py
tbot_api/enums/content_type.py
tbot_api/enums/dice_emoji.py
tbot_api/enums/inline_query_result_type.py
tbot_api/enums/input_media_type.py
tbot_api/enums/mask_position_point.py
tbot_api/enums/menu_button_type.py
tbot_api/enums/message_entity_type.py
tbot_api/enums/parse_mode.py
tbot_api/enums/poll_type.py
tbot_api/enums/sticker_type.py
tbot_api/enums/topic_icon_color.py
tbot_api/enums/update_type.py
tbot_api/methods/__init__.py
tbot_api/methods/add_sticker_to_set.py
tbot_api/methods/answer_callback_query.py
tbot_api/methods/answer_inline_query.py
tbot_api/methods/answer_pre_checkout_query.py
tbot_api/methods/answer_shipping_query.py
tbot_api/methods/answer_web_app_query.py
tbot_api/methods/approve_chat_join_request.py
tbot_api/methods/ban_chat_member.py
tbot_api/methods/ban_chat_sender_chat.py
tbot_api/methods/base.py
tbot_api/methods/close.py
tbot_api/methods/close_forum_topic.py
tbot_api/methods/close_general_forum_topic.py
tbot_api/methods/copy_message.py
tbot_api/methods/create_chat_invite_link.py
tbot_api/methods/create_forum_topic.py
tbot_api/methods/create_invoice_link.py
tbot_api/methods/create_new_sticker_set.py
tbot_api/methods/decline_chat_join_request.py
tbot_api/methods/delete_chat_photo.py
tbot_api/methods/delete_chat_sticker_set.py
tbot_api/methods/delete_forum_topic.py
tbot_api/methods/delete_message.py
tbot_api/methods/delete_my_commands.py
tbot_api/methods/delete_sticker_from_set.py
tbot_api/methods/delete_webhook.py
tbot_api/methods/edit_chat_invite_link.py
tbot_api/methods/edit_forum_topic.py
tbot_api/methods/edit_general_forum_topic.py
tbot_api/methods/edit_message_caption.py
tbot_api-1.0.dist-info/METADATA
tbot_api-1.0.dist-info/WHEEL
tbot_api-1.0.dist-info/RECORD
